MANIFEST.in
README.md
setup.cfg
setup.py
versioneer.py
microhapulator/__init__.py
microhapulator/__main__.py
microhapulator/_version.py
microhapulator/contain.py
microhapulator/contrib.py
microhapulator/diff.py
microhapulator/dist.py
microhapulator/mix.py
microhapulator/panel.py
microhapulator/prob.py
microhapulator/profile.py
microhapulator/seq.py
microhapulator/sim.py
microhapulator/type.py
microhapulator/unite.py
microhapulator.egg-info/PKG-INFO
microhapulator.egg-info/SOURCES.txt
microhapulator.egg-info/dependency_links.txt
microhapulator.egg-info/entry_points.txt
microhapulator.egg-info/requires.txt
microhapulator.egg-info/top_level.txt
microhapulator.egg-info/zip-safe
microhapulator/cli/__init__.py
microhapulator/cli/contain.py
microhapulator/cli/contrib.py
microhapulator/cli/diff.py
microhapulator/cli/dist.py
microhapulator/cli/mix.py
microhapulator/cli/prob.py
microhapulator/cli/seq.py
microhapulator/cli/sim.py
microhapulator/cli/type.py
microhapulator/cli/unite.py
microhapulator/data/.gitignore
microhapulator/data/panel-alpha-legacy.fasta
microhapulator/data/panel-alpha-legacy.txt
microhapulator/data/panel-beta-legacy.fasta
microhapulator/data/panel-beta-legacy.txt
microhapulator/data/profile-schema.json
microhapulator/data/usa-demographics.tsv
microhapulator/tests/__init__.py
microhapulator/tests/test_cli.py
microhapulator/tests/test_contain.py
microhapulator/tests/test_contrib.py
microhapulator/tests/test_diff.py
microhapulator/tests/test_dist.py
microhapulator/tests/test_mix.py
microhapulator/tests/test_prob.py
microhapulator/tests/test_profile.py
microhapulator/tests/test_seq.py
microhapulator/tests/test_sim.py
microhapulator/tests/test_type.py
microhapulator/tests/test_unite.py
microhapulator/tests/data/beta.fastq
microhapulator/tests/data/bitusa-profile.json
microhapulator/tests/data/bogus-refr.fa
microhapulator/tests/data/bogus-refr.fa.fai
microhapulator/tests/data/default-panel.fasta.gz
microhapulator/tests/data/diff-comp-1-2.txt
microhapulator/tests/data/diff-comp-1-3.txt
microhapulator/tests/data/diff-comp-1.json
microhapulator/tests/data/diff-comp-2.json
microhapulator/tests/data/diff-comp-3.json
microhapulator/tests/data/dyncut-panel.fasta.gz
microhapulator/tests/data/dyncut-test-reads.bam
