Metadata-Version: 2.1
Name: microhapulator
Version: 0.4.1
Summary: Software package for simulating and analyzing microhaplotype sequence data
Home-page: https://github.com/bioforensics/microhapulator
Author: Daniel Standage
Author-email: daniel.standage@nbacc.dhs.gov
License: UNKNOWN
Platform: UNKNOWN
Classifier: Environment :: Console
Classifier: Framework :: IPython
Classifier: Framework :: Jupyter
Classifier: Intended Audience :: Science/Research
Classifier: Intended Audience :: Legal Industry
Classifier: License :: OSI Approved :: BSD License
Classifier: Programming Language :: Python :: 3
Classifier: Topic :: Scientific/Engineering :: Bio-Informatics
